docs/conf.py
octomachinery/__init__.py
octomachinery/app/__init__.py
octomachinery/app/config.py
octomachinery/app/action/config.py
octomachinery/app/action/runner.py
octomachinery/app/routing/__init__.py
octomachinery/app/routing/abc.py
octomachinery/app/routing/decorators.py
octomachinery/app/routing/routers.py
octomachinery/app/routing/webhooks_dispatcher.py
octomachinery/app/runtime/__init__.py
octomachinery/app/runtime/config.py
octomachinery/app/runtime/context.py
octomachinery/app/runtime/installation_utils.py
octomachinery/app/runtime/utils.py
octomachinery/app/server/config.py
octomachinery/app/server/machinery.py
octomachinery/app/server/runner.py
octomachinery/cli/__main__.py
octomachinery/github/api/app_client.py
octomachinery/github/api/raw_client.py
octomachinery/github/api/tokens.py
octomachinery/github/api/utils.py
octomachinery/github/config/app.py
octomachinery/github/entities/action.py
octomachinery/github/entities/app_installation.py
octomachinery/github/errors/__init__.py
octomachinery/github/models/__init__.py
octomachinery/github/models/_compat.py
octomachinery/github/models/action_outcomes.py
octomachinery/github/models/checks_api_requests.py
octomachinery/github/models/events.py
octomachinery/github/models/private_key.py
octomachinery/github/models/utils.py
octomachinery/github/utils/event_utils.py
octomachinery/routing/__init__.py
octomachinery/routing/abc.py
octomachinery/routing/decorators.py
octomachinery/routing/default_router.py
octomachinery/routing/routers.py
octomachinery/routing/webhooks_dispatcher.py
octomachinery/runtime/context.py
octomachinery/runtime/utils.py
octomachinery/utils/asynctools.py
octomachinery/utils/versiontools.py
tests/circular_imports_test.py
tests/conftest.py
tests/app/action/runner_test.py
tests/app/routing/decorators_test.py
tests/app/server/machinery_test.py
tests/github/models/private_key_test.py
tests/github/models/utils_test.py
tests/github/utils/event_utils_test.py
tests/utils/asynctools_test.py
octomachinery-0.3.11.dist-info/LICENSE
octomachinery-0.3.11.dist-info/METADATA
octomachinery-0.3.11.dist-info/WHEEL
octomachinery-0.3.11.dist-info/top_level.txt
octomachinery-0.3.11.dist-info/zip-safe
octomachinery-0.3.11.dist-info/RECORD
