Metadata-Version: 2.1
Name: octomachinery
Version: 0.3.11
Summary: Invisible engine driving octobot machines. Simple, yet powerful.
Home-page: https://octomachinery.dev
Author: Sviatoslav Sydorenko (@webknjaz)
Author-email: wk+octomachinery@sydorenko.org.ua
License: GPLv3+
Project-URL: Chat: Matrix, https://matrix.to/#/#octomachinery:matrix.org
Project-URL: Chat: Matrix (PyBA), https://matrix.to/#/#pyba:matrix.org
Project-URL: Chat: Matrix (@webknjaz), https://matrix.to/#/@webknjaz:matrix.org
Project-URL: CI: GitHub, https://github.com/sanitizers/octomachinery/actions/workflows/ci-cd.yml?query=event:push
Project-URL: Docs: RTD, https://docs.octomachinery.dev
Project-URL: GitHub: issues, https://github.com/sanitizers/octomachinery/issues
Project-URL: GitHub: repo, https://github.com/sanitizers/octomachinery
Keywords: Bot,Framework,Framework for writing GitHub Apps,GitHub,GitHub Actions,GitHub API,GitHub Apps,GitHub Checks API
Classifier: Development Status :: 2 - Pre-Alpha
Classifier: Environment :: Console
Classifier: Environment :: Other Environment
Classifier: Environment :: Web Environment
Classifier: Framework :: AnyIO
Classifier: Framework :: AsyncIO
Classifier: Intended Audience :: Developers
Classifier: Intended Audience :: Information Technology
Classifier: Intended Audience :: System Administrators
Classifier: License :: OSI Approved :: GNU General Public License v3 or later (GPLv3+)
Classifier: Operating System :: OS Independent
Classifier: Operating System :: POSIX
Classifier: Programming Language :: Python
Classifier: Programming Language :: Python :: 3
Classifier: Programming Language :: Python :: 3.7
Classifier: Programming Language :: Python :: 3.8
Classifier: Programming Language :: Python :: 3.9
Classifier: Programming Language :: Python :: Implementation
Classifier: Programming Language :: Python :: Implementation :: CPython
Classifier: Programming Language :: Python :: Implementation :: PyPy
Classifier: Topic :: Internet :: WWW/HTTP
Classifier: Topic :: Internet :: WWW/HTTP :: HTTP Servers
Classifier: Topic :: Software Development
Classifier: Topic :: Software Development :: Libraries
Classifier: Topic :: Software Development :: Libraries :: Application Frameworks
Classifier: Topic :: Software Development :: Libraries :: Python Modules
Classifier: Topic :: Software Development :: Version Control
Classifier: Topic :: Software Development :: Version Control :: Git
Classifier: Topic :: System :: Networking
Classifier: Topic :: Utilities
Classifier: Typing :: Typed
Requires-Python: >=3.7
License-File: LICENSE
Requires-Dist: aiohttp
Requires-Dist: anyio <2.0.0
Requires-Dist: click
Requires-Dist: cryptography
Requires-Dist: environ-config >=19.1.0
Requires-Dist: envparse
Requires-Dist: gidgethub >=4.2.0
Requires-Dist: pyjwt[crypto]
Requires-Dist: pyyaml
Requires-Dist: sentry-sdk
Requires-Dist: setuptools-scm
Provides-Extra: docs
Requires-Dist: sphinx ; extra == 'docs'
Requires-Dist: sphinxcontrib-apidoc ; extra == 'docs'
Requires-Dist: furo ; extra == 'docs'
Provides-Extra: testing
Requires-Dist: pytest ; extra == 'testing'
Requires-Dist: pytest-aiohttp ; extra == 'testing'
Requires-Dist: pytest-cov ; extra == 'testing'
Requires-Dist: pytest-xdist ; extra == 'testing'
